jce/__init__.py
jce/__main__.py
jce/log.py
jce/py.typed
jce/types.py
jcestruct-0.1.5.dist-info/LICENSE
jcestruct-0.1.5.dist-info/WHEEL
jcestruct-0.1.5.dist-info/METADATA
jcestruct-0.1.5.dist-info/RECORD
