Metadata-Version: 2.1
Name: jcestruct
Version: 0.1.5
Summary: JCE Encode/Decode
Home-page: https://github.com/yanyongyu/JceStruct
License: MIT
Keywords: jce
Author: yanyongyu
Author-email: yanyongyu_1@126.com
Requires-Python: >=3.7,<4.0
Classifier: License :: OSI Approved :: MIT License
Classifier: Programming Language :: Python :: 3
Classifier: Programming Language :: Python :: 3.10
Classifier: Programming Language :: Python :: 3.7
Classifier: Programming Language :: Python :: 3.8
Classifier: Programming Language :: Python :: 3.9
Requires-Dist: pydantic (>=1.8.1,<2.0.0)
Requires-Dist: typing-extensions (>=3.7.4,<5.0.0)
Project-URL: Documentation, https://github.com/yanyongyu/JceStruct#readme
Project-URL: Repository, https://github.com/yanyongyu/JceStruct
